dlds_discrete/__init__.py
dlds_discrete/create_params.py
dlds_discrete/main_functions.py
dlds_discrete/train_discrete_model_example.py
dlds_discrete/test/__init__.py
dlds_discrete/test/main_functions.py
dLDS_discrete-0.0.97.dist-info/LICENSE.txt
dLDS_discrete-0.0.97.dist-info/METADATA
dLDS_discrete-0.0.97.dist-info/WHEEL
dLDS_discrete-0.0.97.dist-info/top_level.txt
dLDS_discrete-0.0.97.dist-info/RECORD
