Metadata-Version: 2.1
Name: dLDS-discrete
Version: 0.0.97
Summary: dLDS discrete model package
Author: noga mudrik
Author-email: <nmudrik1@jhmi.edu>
Classifier: Programming Language :: Python :: 3
Classifier: License :: OSI Approved :: MIT License
Classifier: Operating System :: OS Independent
Requires-Python: >=3.8
License-File: LICENSE.txt
Requires-Dist: numpy
Requires-Dist: matplotlib
Requires-Dist: scipy
Requires-Dist: pandas
Requires-Dist: webcolors
Requires-Dist: seaborn
Requires-Dist: colormap
Requires-Dist: sklearn
Requires-Dist: pylops
Requires-Dist: dill
Requires-Dist: mat73
Requires-Dist: easydev
